civic_auth/__init__.py
civic_auth/auth.py
civic_auth/exceptions.py
civic_auth/storage.py
civic_auth/types.py
civic_auth/utils.py
civic_auth/integrations/__init__.py
civic_auth/integrations/django.py
civic_auth/integrations/fastapi.py
civic_auth/integrations/flask.py
civic_auth-0.1.2.dist-info/METADATA
civic_auth-0.1.2.dist-info/WHEEL
civic_auth-0.1.2.dist-info/licenses/LICENSE
civic_auth-0.1.2.dist-info/RECORD
