Metadata-Version: 2.4
Name: civic-auth
Version: 0.1.2
Summary: Python SDK for Civic Auth server-side authentication
Project-URL: Homepage, https://github.com/civicteam/civic-auth-py
Project-URL: Documentation, https://docs.civic.com
Project-URL: Repository, https://github.com/civicteam/civic-auth-py
Project-URL: Issues, https://github.com/civicteam/civic-auth-py/issues
Author-email: Daniel Kelleher <daniel@civic.com>
License: MIT
License-File: LICENSE
Keywords: auth,authentication,civic,oauth,oidc
Classifier: Development Status :: 4 - Beta
Classifier: Intended Audience :: Developers
Classifier: License :: OSI Approved :: MIT License
Classifier: Programming Language :: Python :: 3
Classifier: Programming Language :: Python :: 3.8
Classifier: Programming Language :: Python :: 3.9
Classifier: Programming Language :: Python :: 3.10
Classifier: Programming Language :: Python :: 3.11
Classifier: Programming Language :: Python :: 3.12
Classifier: Topic :: Internet :: WWW/HTTP
Classifier: Topic :: Security
Classifier: Topic :: Software Development :: Libraries :: Python Modules
Requires-Python: >=3.8
Requires-Dist: cryptography>=41.0.0
Requires-Dist: httpx>=0.25.0
Requires-Dist: pyjwt>=2.8.0
Provides-Extra: all
Requires-Dist: django>=4.2.0; extra == 'all'
Requires-Dist: fastapi>=0.104.0; extra == 'all'
Requires-Dist: flask[async]>=3.0.0; extra == 'all'
Provides-Extra: dev
Requires-Dist: black>=23.0.0; extra == 'dev'
Requires-Dist: build>=1.0.0; extra == 'dev'
Requires-Dist: mypy>=1.0.0; extra == 'dev'
Requires-Dist: pytest-asyncio>=0.21.0; extra == 'dev'
Requires-Dist: pytest-cov>=4.0.0; extra == 'dev'
Requires-Dist: pytest>=7.0.0; extra == 'dev'
Requires-Dist: ruff>=0.1.0; extra == 'dev'
Requires-Dist: twine>=4.0.0; extra == 'dev'
Provides-Extra: django
Requires-Dist: django>=4.2.0; extra == 'django'
Provides-Extra: fastapi
Requires-Dist: fastapi>=0.104.0; extra == 'fastapi'
Provides-Extra: flask
Requires-Dist: flask[async]>=3.0.0; extra == 'flask'
